Metadata-Version: 1.1
Name: Flask-Admin-Toggle-Control
Version: 0.1.3
Summary: Toggle control for Flask Admin inline form.
Home-page: https://github.com/artemShelest/flask-admin-toggle-control
Author: Artem Shelest
Author-email: artem.e.shelest@gmail.com
License: MIT
Keywords: flask-admin,inline,form,control,bool,boolean,toggle
Platform: any
Classifier: Development Status :: 4 - Beta
Classifier: Intended Audience :: Developers
Classifier: License :: OSI Approved :: MIT License
Classifier: Topic :: Software Development :: Libraries :: Python Modules
Classifier: Programming Language :: Python
Classifier: Programming Language :: Python :: 2.7
Classifier: Programming Language :: Python :: 3
Classifier: Programming Language :: Python :: 3.4
Classifier: Programming Language :: Python :: 3.5
Classifier: Programming Language :: Python :: 3.6
Classifier: Programming Language :: Python :: 3.7
